edge_gemma_speak/__init__.py
edge_gemma_speak/cli.py
edge_gemma_speak/voice_assistant.py
edge_gemma_speak-0.1.1.dist-info/licenses/LICENSE
edge_gemma_speak-0.1.1.dist-info/METADATA
edge_gemma_speak-0.1.1.dist-info/WHEEL
edge_gemma_speak-0.1.1.dist-info/entry_points.txt
edge_gemma_speak-0.1.1.dist-info/top_level.txt
edge_gemma_speak-0.1.1.dist-info/RECORD
