Metadata-Version: 2.4
Name: edge_gemma_speak
Version: 0.1.1
Summary: Edge-based voice assistant using Gemma LLM with STT and TTS capabilities
Home-page: https://github.com/yourusername/edge_gemma_speak
Author: MimicLab, Sogang University
Author-email: 
License: MIT
Project-URL: Homepage, https://github.com/yourusername/edge_gemma_speak
Classifier: Development Status :: 3 - Alpha
Classifier: Intended Audience :: Developers
Classifier: Programming Language :: Python :: 3
Classifier: Programming Language :: Python :: 3.8
Classifier: Programming Language :: Python :: 3.9
Classifier: Programming Language :: Python :: 3.10
Classifier: Programming Language :: Python :: 3.11
Requires-Python: >=3.8
License-File: LICENSE
Requires-Dist: torch>=2.0.0
Requires-Dist: numpy
Requires-Dist: SpeechRecognition
Requires-Dist: faster-whisper
Requires-Dist: llama-cpp-python
Requires-Dist: edge-tts
Requires-Dist: pygame
Requires-Dist: sounddevice
Requires-Dist: soundfile
Requires-Dist: gradio
Requires-Dist: flask
Requires-Dist: pyaudio
Dynamic: home-page
Dynamic: license-file
Dynamic: requires-python
